{
    "network": "mainnet",
    "bentoBox": {
        "enable": true,
        "address": "0xF5BCE5077908a1b7370B9ae04AdC565EBd643966",
        "startBlock": 12094175
    },
    "degenBox": {
        "enable": true,
        "address": "0xd96f48665a1410C0cd669A88898ecA36B9Fc2cce",
        "startBlock": 13418156
    },
    "magicApe": {
        "enable": true,
        "address": "0xf35b31B941D94B249EaDED041DB1b05b7097fEb6",
        "startBlock": 16656455,
        "stakingAddress": "0x5954aB967Bc958940b7EB73ee84797Dc8a2AFbb9",
        "stakingStartBlock": 16525000
    }
}